redditharbor/__init__.py
redditharbor/login.py
redditharbor/dock/__init__.py
redditharbor/dock/pipeline.py
redditharbor/utils/__init__.py
redditharbor/utils/download.py
redditharbor/utils/fetch.py
redditharbor/utils/metrics.py
redditharbor/utils/subreddit_collections.py
redditharbor-0.3.dist-info/licenses/LICENSE
redditharbor-0.3.dist-info/METADATA
redditharbor-0.3.dist-info/WHEEL
redditharbor-0.3.dist-info/top_level.txt
redditharbor-0.3.dist-info/RECORD
