Metadata-Version: 2.4
Name: redditharbor
Version: 0.3
Summary: Effortlessly collect and store Reddit data in your database.
Home-page: https://github.com/socius-org/RedditHarbor/
Download-URL: https://github.com/socius-org/RedditHarbor/archive/refs/tags/0.3.tar.gz
Author: Nick Oh
Author-email: nick.sh.oh@socius.org
License: MIT
Project-URL: Bug Reports, https://github.com/socius-org/RedditHarbor/issues
Project-URL: Source, https://github.com/socius-org/RedditHarbor/
Project-URL: Documentation, https://github.com/socius-org/RedditHarbor/blob/main/README.md
Keywords: Reddit,Supabase,reddit-api,database,reddit-crawler,reddit-scraper
Classifier: Development Status :: 3 - Alpha
Classifier: Intended Audience :: Developers
Classifier: Intended Audience :: Science/Research
Classifier: License :: OSI Approved :: MIT License
Classifier: Operating System :: OS Independent
Classifier: Programming Language :: Python :: 3
Classifier: Programming Language :: Python :: 3.8
Classifier: Programming Language :: Python :: 3.9
Classifier: Programming Language :: Python :: 3.10
Classifier: Programming Language :: Python :: 3.11
Classifier: Programming Language :: Python :: 3.12
Classifier: Programming Language :: Python :: 3.13
Classifier: Topic :: Software Development :: Libraries :: Python Modules
Classifier: Topic :: Internet :: WWW/HTTP :: Dynamic Content
Classifier: Topic :: Database
Requires-Python: >=3.8
License-File: LICENSE
Requires-Dist: praw>=7.7.1
Requires-Dist: supabase>=1.0.3
Requires-Dist: rich>=13.4.2
Requires-Dist: python-dotenv>=1.0.0
Requires-Dist: pillow<12.0.0,>=10.3.0
Requires-Dist: requests<3.0.0,>=2.32.4
Provides-Extra: pii
Requires-Dist: spacy<4.0.0,>=3.7.0; extra == "pii"
Requires-Dist: presidio-analyzer<3.0.0,>=2.2.351; extra == "pii"
Requires-Dist: presidio-anonymizer<3.0.0,>=2.2.351; extra == "pii"
Dynamic: author
Dynamic: author-email
Dynamic: classifier
Dynamic: description
Dynamic: description-content-type
Dynamic: download-url
Dynamic: home-page
Dynamic: keywords
Dynamic: license
Dynamic: license-file
Dynamic: project-url
Dynamic: provides-extra
Dynamic: requires-dist
Dynamic: requires-python
Dynamic: summary
